fisica_sdk/__init__.py
fisica_sdk/analyzer.py
fisica_sdk/base_uart.py
fisica_sdk/bluetooth_handler.py
fisica_sdk/device.py
fisica_sdk/exporter.py
fisica_sdk/fisica_sdk.py
fisica_sdk/gui_viewer.py
fisica_sdk/models.py
fisica_sdk/parser.py
fisica_sdk/port_scanner.py
fisica_sdk/receiver.py
fisica_sdk/serial_handler.py
fisica_sdk/serial_uart.py
fisica_sdk/utils.py
fisica_sdk/version_utils.py
fisica_sdk/visualizer.py
fisica-1.0.1.dist-info/METADATA
fisica-1.0.1.dist-info/WHEEL
fisica-1.0.1.dist-info/top_level.txt
fisica-1.0.1.dist-info/RECORD
