Metadata-Version: 2.4
Name: fisica
Version: 1.0.1
Summary: Care&Co Foot pressure analysis and visualization SDK
Home-page: https://github.com/Care-Co/
Author: Care&Co
Author-email: carencoinc@carenco.kr
License: MIT
Project-URL: Bug Tracker, https://github.com/Care-Co/fisica_sdk/issues
Project-URL: Documentation, https://fisica-sdk.readthedocs.io/
Project-URL: Source Code, https://github.com/Care-Co/fisica_sdk
Keywords: foot pressure analysis medical sensor visualization
Classifier: Programming Language :: Python :: 3
Classifier: Programming Language :: Python :: 3.8
Classifier: Programming Language :: Python :: 3.9
Classifier: Programming Language :: Python :: 3.10
Classifier: Programming Language :: Python :: 3.11
Classifier: Programming Language :: Python :: 3.12
Classifier: License :: OSI Approved :: MIT License
Classifier: Operating System :: OS Independent
Classifier: Development Status :: 3 - Alpha
Classifier: Intended Audience :: Developers
Classifier: Intended Audience :: Healthcare Industry
Classifier: Topic :: Scientific/Engineering :: Medical Science Apps.
Classifier: Topic :: Scientific/Engineering :: Human Machine Interfaces
Classifier: Topic :: Software Development :: Libraries :: Python Modules
Requires-Python: >=3.8
Requires-Dist: numpy>=1.21
Requires-Dist: opencv-python>=4.5
Requires-Dist: requests>=2.25
Requires-Dist: packaging>=21.0
Requires-Dist: Pillow>=8.0
Requires-Dist: pyserial>=3.5
Requires-Dist: PyQt5>=5.15
Requires-Dist: bleak>=0.22.3
Dynamic: author
Dynamic: author-email
Dynamic: classifier
Dynamic: description
Dynamic: description-content-type
Dynamic: home-page
Dynamic: keywords
Dynamic: license
Dynamic: project-url
Dynamic: requires-dist
Dynamic: requires-python
Dynamic: summary
